Metadata-Version: 2.1
Name: django-cryptography-django5
Version: 2.2
Summary: Easily encrypt data in Django - Fork for Django 5 support
Home-page: https://github.com/chrisclark/django-cryptography
Author: George Marshall
Author-email: george@georgemarshall.name
License: BSD-3-Clause
Project-URL: Bug Reports, https://github.com/georgemarshall/django-cryptography/issues
Project-URL: Source, https://github.com/chrisclark/django-cryptography
Project-URL: Documentation, https://django-cryptography.readthedocs.io
Classifier: Development Status :: 2 - Pre-Alpha
Classifier: Environment :: Web Environment
Classifier: Framework :: Django
Classifier: Framework :: Django :: 3.2
Classifier: Framework :: Django :: 4.0
Classifier: Framework :: Django :: 5.0
Classifier: Intended Audience :: Developers
Classifier: License :: OSI Approved :: BSD License
Classifier: Operating System :: OS Independent
Classifier: Programming Language :: Python
Classifier: Programming Language :: Python :: 3
Classifier: Programming Language :: Python :: 3.8
Classifier: Programming Language :: Python :: 3.9
Classifier: Programming Language :: Python :: 3.10
Classifier: Programming Language :: Python :: 3.11
Classifier: Programming Language :: Python :: 3.12
Classifier: Programming Language :: Python :: 3 :: Only
Classifier: Topic :: Internet :: WWW/HTTP
Classifier: Topic :: Security :: Cryptography
Requires-Python: >=3.8
License-File: LICENSE
Requires-Dist: Django>=3.2
Requires-Dist: cryptography>=42.0
Requires-Dist: django-appconf
Provides-Extra: mypy
Requires-Dist: django-stubs; extra == "mypy"
Requires-Dist: mypy; extra == "mypy"
